test_automation_package_dsm/__init__.py
test_automation_package_dsm-0.0.3.dist-info/LICENSE
test_automation_package_dsm-0.0.3.dist-info/METADATA
test_automation_package_dsm-0.0.3.dist-info/WHEEL
test_automation_package_dsm-0.0.3.dist-info/top_level.txt
test_automation_package_dsm-0.0.3.dist-info/RECORD
