Metadata-Version: 2.1
Name: test-automation-package-dsm
Version: 0.0.3
Summary: Used for automated test cases to test apps build in Mendix
Author-email: Tim Verlinde <tim.verlinde@dsm.com>
License: Copyright (c) 2018 The Python Packaging Authority        
Classifier: Programming Language :: Python :: 3
Classifier: License :: OSI Approved :: MIT License
Classifier: Operating System :: OS Independent
Requires-Python: >=3.7
License-File: LICENSE
Requires-Dist: easygui (==0.98.3)
Requires-Dist: selenium (==4.4.3)
Requires-Dist: chromedriver-py (~=105.0.5195.52)
